tinynetrc.py
tinynetrc-1.3.1.dist-info/LICENSE
tinynetrc-1.3.1.dist-info/METADATA
tinynetrc-1.3.1.dist-info/WHEEL
tinynetrc-1.3.1.dist-info/top_level.txt
tinynetrc-1.3.1.dist-info/RECORD
