Metadata-Version: 2.1
Name: tinynetrc
Version: 1.3.1
Summary: Read and write .netrc files.
Home-page: https://github.com/sloria/tinynetrc
Author: Steven Loria
Author-email: sloria1@gmail.com
License: MIT
Keywords: netrc posix
Platform: UNKNOWN
Classifier: Intended Audience :: Developers
Classifier: License :: OSI Approved :: MIT License
Classifier: Programming Language :: Python :: 2
Classifier: Programming Language :: Python :: 2.7
Classifier: Programming Language :: Python :: 3
Classifier: Programming Language :: Python :: 3.5
Classifier: Programming Language :: Python :: 3.6
Classifier: Programming Language :: Python :: 3.7
Classifier: Programming Language :: Python :: Implementation :: CPython
Provides-Extra: tests
Provides-Extra: lint
Provides-Extra: dev
License-File: LICENSE
